mod_cli/__init__.py
mod_cli/commands/__init__.py
mod_cli/commands/add.py
mod_cli/commands/build.py
mod_cli/commands/cmds.py
mod_cli/commands/doctor.py
mod_cli/commands/hack.py
mod_cli/commands/init.py
mod_cli/commands/new.py
mod_cli/commands/publish.py
mod_cli/commands/workspace.py
mod_cli/core/__init__.py
mod_cli/core/development/__init__.py
mod_cli/core/development/dev.py
mod_cli/core/dir/__init__.py
mod_cli/core/dir/dir.py
mod_cli/core/git/__init__.py
mod_cli/core/git/git.py
mod_cli/core/modfile/__init__.py
mod_cli/core/modfile/mod.py
mod_cli/core/new/__init__.py
mod_cli/core/new/layout.py
mod_cli/core/new/new.py
mod_cli/core/package/__init__.py
mod_cli/core/package/package.py
mod_cli/core/project/__init__.py
mod_cli/core/setup/__init__.py
mod_cli/core/setup/config.py
mod_cli/core/setup/deps.py
mod_cli/core/workspace/__init__.py
mod_cli/main.py
mod_cli/templates/.gitignore
mod_cli/templates/README.md
mod_cli/templates/Taskfile.yml
mod_cli/templates/__init__.mojo
mod_cli/templates/lib.mojo
mod_cli/templates/main.mojo
mod_cli/templates/mod.lock
mod_cli/templates/mod.toml
mod_cli/templates/mod2.toml
mod_cli/templates/mod3.lock
mod_cli/templates/mod3.toml
mod_cli/utils/__init__.py
mod_cli/utils/path.py
mod_cli/utils/validate.py
mod_cli-0.1.2.dist-info/METADATA
mod_cli-0.1.2.dist-info/WHEEL
mod_cli-0.1.2.dist-info/entry_points.txt
mod_cli-0.1.2.dist-info/RECORD
