Metadata-Version: 2.1
Name: mod-cli
Version: 0.1.2
Summary: a CLI Tool for Mojo Package Manager
Author: Henry.Huang
Author-email: hhglory@outlook.com
Requires-Python: >=3.10,<4.0
Classifier: Programming Language :: Python :: 3
Classifier: Programming Language :: Python :: 3.10
Classifier: Programming Language :: Python :: 3.11
Classifier: Programming Language :: Python :: 3.12
Requires-Dist: jinja2 (>=3.1.2,<4.0.0)
Requires-Dist: loguru (>=0.7.2,<0.8.0)
Requires-Dist: rich (>=13.7.0,<14.0.0)
Requires-Dist: tomlkit (>=0.12.3,<0.13.0)
Requires-Dist: typer[all] (>=0.9.0,<0.10.0)
